{
  "updatedAt": "2026-06-04T14:39:42-04:00",
  "today": {
    "date": "2026-06-04",
    "focusMinutes": 52
  },
  "anki": {
    "today": {
      "reviews": 207,
      "new": 43,
      "minutes": 27.2
    },
    "total": {
      "cards": 35974,
      "mature": 96
    },
    "streak": 2,
    "history": [
      {
        "date": "2026-05-06",
        "reviews": 135,
        "new": 182,
        "minutes": 18.0
      },
      {
        "date": "2026-05-07",
        "reviews": 142,
        "new": 211,
        "minutes": 28.4
      },
      {
        "date": "2026-05-08",
        "reviews": 111,
        "new": 126,
        "minutes": 23.9
      },
      {
        "date": "2026-05-09",
        "reviews": 0,
        "new": 0,
        "minutes": 0
      },
      {
        "date": "2026-05-10",
        "reviews": 0,
        "new": 0,
        "minutes": 0
      },
      {
        "date": "2026-05-11",
        "reviews": 216,
        "new": 143,
        "minutes": 29.1
      },
      {
        "date": "2026-05-12",
        "reviews": 0,
        "new": 0,
        "minutes": 0
      },
      {
        "date": "2026-05-13",
        "reviews": 0,
        "new": 0,
        "minutes": 0
      },
      {
        "date": "2026-05-14",
        "reviews": 0,
        "new": 0,
        "minutes": 0
      },
      {
        "date": "2026-05-15",
        "reviews": 0,
        "new": 0,
        "minutes": 0
      },
      {
        "date": "2026-05-16",
        "reviews": 0,
        "new": 0,
        "minutes": 0
      },
      {
        "date": "2026-05-17",
        "reviews": 0,
        "new": 0,
        "minutes": 0
      },
      {
        "date": "2026-05-18",
        "reviews": 0,
        "new": 0,
        "minutes": 0
      },
      {
        "date": "2026-05-19",
        "reviews": 0,
        "new": 0,
        "minutes": 0
      },
      {
        "date": "2026-05-20",
        "reviews": 0,
        "new": 0,
        "minutes": 0
      },
      {
        "date": "2026-05-21",
        "reviews": 0,
        "new": 0,
        "minutes": 0
      },
      {
        "date": "2026-05-22",
        "reviews": 0,
        "new": 0,
        "minutes": 0
      },
      {
        "date": "2026-05-23",
        "reviews": 0,
        "new": 0,
        "minutes": 0
      },
      {
        "date": "2026-05-24",
        "reviews": 0,
        "new": 0,
        "minutes": 0
      },
      {
        "date": "2026-05-25",
        "reviews": 33,
        "new": 14,
        "minutes": 4.1
      },
      {
        "date": "2026-05-26",
        "reviews": 153,
        "new": 55,
        "minutes": 17.6
      },
      {
        "date": "2026-05-27",
        "reviews": 54,
        "new": 91,
        "minutes": 10.0
      },
      {
        "date": "2026-05-28",
        "reviews": 114,
        "new": 91,
        "minutes": 18.8
      },
      {
        "date": "2026-05-29",
        "reviews": 43,
        "new": 64,
        "minutes": 6.6
      },
      {
        "date": "2026-05-30",
        "reviews": 86,
        "new": 66,
        "minutes": 11.2
      },
      {
        "date": "2026-05-31",
        "reviews": 75,
        "new": 54,
        "minutes": 15.3
      },
      {
        "date": "2026-06-01",
        "reviews": 0,
        "new": 0,
        "minutes": 0
      },
      {
        "date": "2026-06-02",
        "reviews": 0,
        "new": 0,
        "minutes": 0
      },
      {
        "date": "2026-06-03",
        "reviews": 1,
        "new": 1,
        "minutes": 0.7
      },
      {
        "date": "2026-06-04",
        "reviews": 207,
        "new": 43,
        "minutes": 27.2
      }
    ]
  },
  "course": {
    "updatedAt": "2026-06-04T08:43:44.189Z",
    "lastLesson": {
      "id": "a1/6_3.mp4",
      "title": "6 3 · 形容词阴性变化",
      "course": "a1",
      "time": 0.993392
    },
    "courses": [
      {
        "id": "phonetics",
        "label": "A0",
        "watchedSeconds": 19072.65,
        "durationSeconds": 19072.65,
        "percent": 100.0
      },
      {
        "id": "a1",
        "label": "A1",
        "watchedSeconds": 18936.1,
        "durationSeconds": 79062.89,
        "percent": 23.95
      },
      {
        "id": "a2",
        "label": "A2",
        "watchedSeconds": 0.0,
        "durationSeconds": 93834.33,
        "percent": 0.0
      },
      {
        "id": "b1",
        "label": "B1",
        "watchedSeconds": 0.0,
        "durationSeconds": 63339.68,
        "percent": 0.0
      },
      {
        "id": "b2",
        "label": "B2",
        "watchedSeconds": 0.0,
        "durationSeconds": 232009.4,
        "percent": 0.0
      }
    ],
    "total": {
      "watchedSeconds": 38008.75,
      "durationSeconds": 487318.95,
      "percent": 7.8
    },
    "today": {
      "minutes": 315.6,
      "goalMinutes": 60,
      "goalPercent": 100
    }
  },
  "reading": {
    "today": {
      "date": "2026-06-04",
      "sets": 0.2564102564102564,
      "questions": 10,
      "correct": 9,
      "minutes": 25.2,
      "tests": [
        {
          "test": "test01",
          "answered": 10,
          "correct": 9,
          "total": 39
        }
      ],
      "accuracy": 90.0,
      "goalPercent": 25.64
    },
    "history": [
      {
        "date": "2026-05-06",
        "sets": 0,
        "questions": 0,
        "correct": 0,
        "minutes": 0,
        "tests": [],
        "accuracy": 0,
        "goalPercent": 0.0
      },
      {
        "date": "2026-05-07",
        "sets": 0,
        "questions": 0,
        "correct": 0,
        "minutes": 0,
        "tests": [],
        "accuracy": 0,
        "goalPercent": 0.0
      },
      {
        "date": "2026-05-08",
        "sets": 0,
        "questions": 0,
        "correct": 0,
        "minutes": 0,
        "tests": [],
        "accuracy": 0,
        "goalPercent": 0.0
      },
      {
        "date": "2026-05-09",
        "sets": 0,
        "questions": 0,
        "correct": 0,
        "minutes": 0,
        "tests": [],
        "accuracy": 0,
        "goalPercent": 0.0
      },
      {
        "date": "2026-05-10",
        "sets": 0,
        "questions": 0,
        "correct": 0,
        "minutes": 0,
        "tests": [],
        "accuracy": 0,
        "goalPercent": 0.0
      },
      {
        "date": "2026-05-11",
        "sets": 0,
        "questions": 0,
        "correct": 0,
        "minutes": 0,
        "tests": [],
        "accuracy": 0,
        "goalPercent": 0.0
      },
      {
        "date": "2026-05-12",
        "sets": 0,
        "questions": 0,
        "correct": 0,
        "minutes": 0,
        "tests": [],
        "accuracy": 0,
        "goalPercent": 0.0
      },
      {
        "date": "2026-05-13",
        "sets": 0,
        "questions": 0,
        "correct": 0,
        "minutes": 0,
        "tests": [],
        "accuracy": 0,
        "goalPercent": 0.0
      },
      {
        "date": "2026-05-14",
        "sets": 0,
        "questions": 0,
        "correct": 0,
        "minutes": 0,
        "tests": [],
        "accuracy": 0,
        "goalPercent": 0.0
      },
      {
        "date": "2026-05-15",
        "sets": 0,
        "questions": 0,
        "correct": 0,
        "minutes": 0,
        "tests": [],
        "accuracy": 0,
        "goalPercent": 0.0
      },
      {
        "date": "2026-05-16",
        "sets": 0,
        "questions": 0,
        "correct": 0,
        "minutes": 0,
        "tests": [],
        "accuracy": 0,
        "goalPercent": 0.0
      },
      {
        "date": "2026-05-17",
        "sets": 0,
        "questions": 0,
        "correct": 0,
        "minutes": 0,
        "tests": [],
        "accuracy": 0,
        "goalPercent": 0.0
      },
      {
        "date": "2026-05-18",
        "sets": 0,
        "questions": 0,
        "correct": 0,
        "minutes": 0,
        "tests": [],
        "accuracy": 0,
        "goalPercent": 0.0
      },
      {
        "date": "2026-05-19",
        "sets": 0,
        "questions": 0,
        "correct": 0,
        "minutes": 0,
        "tests": [],
        "accuracy": 0,
        "goalPercent": 0.0
      },
      {
        "date": "2026-05-20",
        "sets": 0,
        "questions": 0,
        "correct": 0,
        "minutes": 0,
        "tests": [],
        "accuracy": 0,
        "goalPercent": 0.0
      },
      {
        "date": "2026-05-21",
        "sets": 0,
        "questions": 0,
        "correct": 0,
        "minutes": 0,
        "tests": [],
        "accuracy": 0,
        "goalPercent": 0.0
      },
      {
        "date": "2026-05-22",
        "sets": 0,
        "questions": 0,
        "correct": 0,
        "minutes": 0,
        "tests": [],
        "accuracy": 0,
        "goalPercent": 0.0
      },
      {
        "date": "2026-05-23",
        "sets": 0,
        "questions": 0,
        "correct": 0,
        "minutes": 0,
        "tests": [],
        "accuracy": 0,
        "goalPercent": 0.0
      },
      {
        "date": "2026-05-24",
        "sets": 0,
        "questions": 0,
        "correct": 0,
        "minutes": 0,
        "tests": [],
        "accuracy": 0,
        "goalPercent": 0.0
      },
      {
        "date": "2026-05-25",
        "sets": 0,
        "questions": 0,
        "correct": 0,
        "minutes": 0,
        "tests": [],
        "accuracy": 0,
        "goalPercent": 0.0
      },
      {
        "date": "2026-05-26",
        "sets": 0,
        "questions": 0,
        "correct": 0,
        "minutes": 0,
        "tests": [],
        "accuracy": 0,
        "goalPercent": 0.0
      },
      {
        "date": "2026-05-27",
        "sets": 0,
        "questions": 0,
        "correct": 0,
        "minutes": 0,
        "tests": [],
        "accuracy": 0,
        "goalPercent": 0.0
      },
      {
        "date": "2026-05-28",
        "sets": 0,
        "questions": 0,
        "correct": 0,
        "minutes": 0,
        "tests": [],
        "accuracy": 0,
        "goalPercent": 0.0
      },
      {
        "date": "2026-05-29",
        "sets": 0,
        "questions": 0,
        "correct": 0,
        "minutes": 0,
        "tests": [],
        "accuracy": 0,
        "goalPercent": 0.0
      },
      {
        "date": "2026-05-30",
        "sets": 0,
        "questions": 0,
        "correct": 0,
        "minutes": 0,
        "tests": [],
        "accuracy": 0,
        "goalPercent": 0.0
      },
      {
        "date": "2026-05-31",
        "sets": 0,
        "questions": 0,
        "correct": 0,
        "minutes": 0,
        "tests": [],
        "accuracy": 0,
        "goalPercent": 0.0
      },
      {
        "date": "2026-06-01",
        "sets": 0,
        "questions": 0,
        "correct": 0,
        "minutes": 0,
        "tests": [],
        "accuracy": 0,
        "goalPercent": 0.0
      },
      {
        "date": "2026-06-02",
        "sets": 0,
        "questions": 0,
        "correct": 0,
        "minutes": 0,
        "tests": [],
        "accuracy": 0,
        "goalPercent": 0.0
      },
      {
        "date": "2026-06-03",
        "sets": 0,
        "questions": 0,
        "correct": 0,
        "minutes": 0,
        "tests": [],
        "accuracy": 0,
        "goalPercent": 0.0
      },
      {
        "date": "2026-06-04",
        "sets": 0.2564102564102564,
        "questions": 10,
        "correct": 9,
        "minutes": 25.2,
        "tests": [
          {
            "test": "test01",
            "answered": 10,
            "correct": 9,
            "total": 39
          }
        ],
        "accuracy": 90.0,
        "goalPercent": 25.64
      }
    ]
  }
}